[
    {
        "nom":"Hammer Slam Bowser",
        "element":"Feu",
        "version":"Supercharger",
        "special":null,
        "sante":871,
        "vitesse":35,
        "armure":30,
        "coup_critique":6,
        "puissance_elementaire":25
    },
    {
        "nom":"Hammer Slam Bowser",
        "element":"Feu",
        "version":"Supercharger",
        "special":"Dark",
        "sante":1126,
        "vitesse":35,
        "armure":30,
        "coup_critique":10,
        "puissance_elementaire":25
    },
    {
        "nom":"Spitfire",
        "element":"Feu",
        "version":"Supercharger",
        "special":"Dark",
        "sante":778,
        "vitesse":50,
        "armure":18,
        "coup_critique":10,
        "puissance_elementaire":25
    },
    {
        "nom":"Spitfire",
        "element":"Feu",
        "version":"Supercharger",
        "special":null,
        "sante":622,
        "vitesse":50,
        "armure":18,
        "coup_critique":8,
        "puissance_elementaire":25
    },
    {
        "nom":"Lava Lance Eruptor",
        "element":"Feu",
        "version":"Supercharger",
        "special":null,
        "sante":902,
        "vitesse":35,
        "armure":24,
        "coup_critique":8,
        "puissance_elementaire":25
    },
    {
        "nom":"Hurricane Jet-Vac",
        "element":"Air",
        "version":"Supercharger",
        "special":null,
        "sante":747,
        "vitesse":43,
        "armure":12,
        "coup_critique":6,
        "puissance_elementaire":25
    },
    {
        "nom":"Hurricane Jet-Vac",
        "element":"Air",
        "version":"Supercharger",
        "special":"Legendary",
        "sante":902,
        "vitesse":43,
        "armure":12,
        "coup_critique":11,
        "puissance_elementaire":25
    },
    {
        "nom":"Stormblade",
        "element":"Air",
        "version":"Supercharger",
        "special":null,
        "sante":684,
        "vitesse":50,
        "armure":6,
        "coup_critique":6,
        "puissance_elementaire":25
    },
    {
        "nom":"Nightfall",
        "element":"Ténèbres",
        "version":"Supercharger",
        "special":null,
        "sante":716,
        "vitesse":43,
        "armure":6,
        "coup_critique":10,
        "puissance_elementaire":25
    },
    {
        "nom":"Smash Hit",
        "element":"Terre",
        "version":"Supercharger",
        "special":"Steel Plated",
        "sante":1244,
        "vitesse":35,
        "armure":24,
        "coup_critique":4,
        "puissance_elementaire":25
    },
    {
        "nom":"Smash Hit",
        "element":"Terre",
        "version":"Supercharger",
        "special":null,
        "sante":1089,
        "vitesse":35,
        "armure":24,
        "coup_critique":2,
        "puissance_elementaire":25
    },
    {
        "nom":"Shark Shooter Terrafin",
        "element":"Terre",
        "version":"Supercharger",
        "special":null,
        "sante":840,
        "vitesse":35,
        "armure":24,
        "coup_critique":4,
        "puissance_elementaire":25
    },
    {
        "nom":"Dino-Rang",
        "element":"Terre",
        "version":"Élite",
        "special":null,
        "sante":2700,
        "vitesse":43,
        "armure":66,
        "coup_critique":26,
        "puissance_elementaire":25
    },
    {
        "nom":"Turbo Charge Donkey Kong",
        "element":"Vie",
        "version":"Supercharger",
        "special":null,
        "sante":1150,
        "vitesse":50,
        "armure":12,
        "coup_critique":2,
        "puissance_elementaire":25
    },
    {
        "nom":"Turbo Charge Donkey Kong",
        "element":"Vie",
        "version":"Supercharger",
        "special":"Dark",
        "sante":1306,
        "vitesse":50,
        "armure":12,
        "coup_critique":6,
        "puissance_elementaire":25
    },
    {
        "nom":"Thrillipede",
        "element":"Vie",
        "version":"Supercharger",
        "special":null,
        "sante":778,
        "vitesse":50,
        "armure":12,
        "coup_critique":8,
        "puissance_elementaire":25
    },
    {
        "nom":"Thrillipede",
        "element":"Vie",
        "version":"Supercharger",
        "special":"Eggcited",
        "sante":933,
        "vitesse":50,
        "armure":12,
        "coup_critique":10,
        "puissance_elementaire":25
    },
    {
        "nom":"Super Shot Stealth Elf",
        "element":"Vie",
        "version":"Supercharger",
        "special":null,
        "sante":591,
        "vitesse":50,
        "armure":12,
        "coup_critique":6,
        "puissance_elementaire":25
    },
    {
        "nom":"Super Shot Stealth Elf",
        "element":"Vie",
        "version":"Supercharger",
        "special":"Dark",
        "sante":747,
        "vitesse":50,
        "armure":12,
        "coup_critique":8,
        "puissance_elementaire":25
    },
    {
        "nom":"Zook",
        "element":"Vie",
        "version":"Élite",
        "special":null,
        "sante":2340,
        "vitesse":43,
        "armure":66,
        "coup_critique":24,
        "puissance_elementaire":25
    },
    {
        "nom":"Astroblast",
        "element":"Lumière",
        "version":"Supercharger",
        "special":null,
        "sante":560,
        "vitesse":35,
        "armure":18,
        "coup_critique":6,
        "puissance_elementaire":25
    },
    {
        "nom":"Astroblast",
        "element":"Lumière",
        "version":"Supercharger",
        "special":"Legendary",
        "sante":716,
        "vitesse":35,
        "armure":18,
        "coup_critique":16,
        "puissance_elementaire":25
    },
    {
        "nom":"Splat",
        "element":"Magie",
        "version":"Supercharger",
        "special":null,
        "sante":747,
        "vitesse":43,
        "armure":6,
        "coup_critique":4,
        "puissance_elementaire":25
    },
    {
        "nom":"Splat",
        "element":"Magie",
        "version":"Supercharger",
        "special":"Power Blue",
        "sante":747,
        "vitesse":43,
        "armure":6,
        "coup_critique":4,
        "puissance_elementaire":25
    },
    {
        "nom":"Big Bubble Pop Fizz",
        "element":"Magie",
        "version":"Supercharger",
        "special":"Birthday Bash",
        "sante":1011,
        "vitesse":43,
        "armure":24,
        "coup_critique":6,
        "puissance_elementaire":25
    },
    {
        "nom":"Big Bubble Pop Fizz",
        "element":"Magie",
        "version":"Supercharger",
        "special":null,
        "sante":933,
        "vitesse":43,
        "armure":24,
        "coup_critique":4,
        "puissance_elementaire":25
    },
    {
        "nom":"Voodood",
        "element":"Magie",
        "version":"Élite",
        "special":null,
        "sante":2610,
        "vitesse":35,
        "armure":48,
        "coup_critique":26,
        "puissance_elementaire":25
    },
    {
        "nom":"High Volt",
        "element":"Tech",
        "version":"Supercharger",
        "special":null,
        "sante":778,
        "vitesse":50,
        "armure":24,
        "coup_critique":2,
        "puissance_elementaire":25
    },
    {
        "nom":"Double Dare Trigger Happy",
        "element":"Tech",
        "version":"Supercharger",
        "special":null,
        "sante":933,
        "vitesse":50,
        "armure":18,
        "coup_critique":6,
        "puissance_elementaire":25
    },
    {
        "nom":"Power Blue Trigger Happy",
        "element":"Tech",
        "version":"Supercharger",
        "special":true,
        "sante":933,
        "vitesse":50,
        "armure":18,
        "coup_critique":6,
        "puissance_elementaire":25
    },
    {
        "nom":"Boomer",
        "element":"Tech",
        "version":"Élite",
        "special":null,
        "sante":2070,
        "vitesse":35,
        "armure":54,
        "coup_critique":30,
        "puissance_elementaire":25
    },
    {
        "nom":"Fiesta",
        "element":"Mort-vivant",
        "version":"Supercharger",
        "special":null,
        "sante":716,
        "vitesse":50,
        "armure":6,
        "coup_critique":4,
        "puissance_elementaire":25
    },
    {
        "nom":"Fiesta",
        "element":"Mort-vivant",
        "version":"Supercharger",
        "special":"Fightful",
        "sante":763,
        "vitesse":50,
        "armure":6,
        "coup_critique":6,
        "puissance_elementaire":25
    },
    {
        "nom":"Bone Bash Roller Brawl",
        "element":"Mort-vivant",
        "version":"Supercharger",
        "special":null,
        "sante":684,
        "vitesse":50,
        "armure":12,
        "coup_critique":6,
        "puissance_elementaire":25
    },
    {
        "nom":"Bone Bash Roller Brawl",
        "element":"Mort-vivant",
        "version":"Supercharger",
        "special":"Legendary",
        "sante":840,
        "vitesse":50,
        "armure":12,
        "coup_critique":16,
        "puissance_elementaire":25
    },
    {
        "nom":"Ghost Roaster",
        "element":"Mort-vivant",
        "version":"Élite",
        "special":null,
        "sante":2520,
        "vitesse":43,
        "armure":60,
        "coup_critique":24,
        "puissance_elementaire":25
    },
    {
        "nom":"Deep Dive Gill Grunt",
        "element":"Eau",
        "version":"Supercharger",
        "special":null,
        "sante":840,
        "vitesse":35,
        "armure":24,
        "coup_critique":6,
        "puissance_elementaire":25
    },
    {
        "nom":"Dive-Clops",
        "element":"Eau",
        "version":"Supercharger",
        "special":null,
        "sante":778,
        "vitesse":35,
        "armure":30,
        "coup_critique":4,
        "puissance_elementaire":25
    },
    {
        "nom":"Dive-Clops",
        "element":"Eau",
        "version":"Supercharger",
        "special":"Missile-Tow",
        "sante":933,
        "vitesse":35,
        "armure":30,
        "coup_critique":6,
        "puissance_elementaire":25
    },
    {
        "nom":"Slam Bam",
        "element":"Eau",
        "version":"Élite",
        "special":null,
        "sante":2790,
        "vitesse":35,
        "armure":66,
        "coup_critique":22,
        "puissance_elementaire":25
    }
]